README
romexpander.py
setup.py
romexpander.egg-info/PKG-INFO
romexpander.egg-info/SOURCES.txt
romexpander.egg-info/dependency_links.txt
romexpander.egg-info/requires.txt
romexpander.egg-info/top_level.txt