Metadata-Version: 1.0
Name: romexpander
Version: 0.4
Summary: NES ROM Expansion script compatible with DvD's ROM Expander Pro.
Home-page: http://www.cdf.utoronto.ca/~g8m/
Author: Devon Meunier
Author-email: devon.meunier@utoronto.ca
License: MIT
Platform: UNKNOWN
